diacamma/__init__.py
diacamma/accounting/__init__.py
diacamma/accounting/build
diacamma/accounting/currency_iso.csv
diacamma/accounting/editors.py
diacamma/accounting/models.py
diacamma/accounting/test_tools.py
diacamma/accounting/tests.py
diacamma/accounting/tests_accounts.py
diacamma/accounting/tests_completed_entries.py
diacamma/accounting/tests_entries.py
diacamma/accounting/tools.py
diacamma/accounting/tools_reports.py
diacamma/accounting/views.py
diacamma/accounting/views_accounts.py
diacamma/accounting/views_admin.py
diacamma/accounting/views_budget.py
diacamma/accounting/views_entries.py
diacamma/accounting/views_other.py
diacamma/accounting/views_reports.py
diacamma/accounting/docs/build_en/doctrees/budget.doctree
diacamma/accounting/docs/build_en/doctrees/costaccounting.doctree
diacamma/accounting/docs/build_en/doctrees/definition.doctree
diacamma/accounting/docs/build_en/doctrees/entity.doctree
diacamma/accounting/docs/build_en/doctrees/environment.pickle
diacamma/accounting/docs/build_en/doctrees/fiscalyear.doctree
diacamma/accounting/docs/build_en/doctrees/index.doctree
diacamma/accounting/docs/build_en/doctrees/model.doctree
diacamma/accounting/docs/build_en/doctrees/reporting.doctree
diacamma/accounting/docs/build_en/doctrees/third.doctree
diacamma/accounting/docs/build_fr/doctrees/budget.doctree
diacamma/accounting/docs/build_fr/doctrees/costaccounting.doctree
diacamma/accounting/docs/build_fr/doctrees/definition.doctree
diacamma/accounting/docs/build_fr/doctrees/entity.doctree
diacamma/accounting/docs/build_fr/doctrees/environment.pickle
diacamma/accounting/docs/build_fr/doctrees/fiscalyear.doctree
diacamma/accounting/docs/build_fr/doctrees/index.doctree
diacamma/accounting/docs/build_fr/doctrees/model.doctree
diacamma/accounting/docs/build_fr/doctrees/reporting.doctree
diacamma/accounting/docs/build_fr/doctrees/third.doctree
diacamma/accounting/docs/en/Makefile
diacamma/accounting/docs/en/account_edit.png
diacamma_financial-2.7.5.25070909.dist-info/licenses/LICENSE
diacamma_financial-2.7.5.25070909.dist-info/METADATA
diacamma_financial-2.7.5.25070909.dist-info/WHEEL
diacamma_financial-2.7.5.25070909.dist-info/top_level.txt
diacamma_financial-2.7.5.25070909.dist-info/RECORD
