Metadata-Version: 2.4
Name: diacamma-financial
Version: 2.7.5.25070909
Summary: Diacamma financial modules for Lucterios framework.
Home-page: http://www.diacamma.org
Author: Lucterios
Author-email: info@diacamma.org
License: GNU General Public License v3
Platform: Any
Classifier: Development Status :: 5 - Production/Stable
Classifier: Environment :: Web Environment
Classifier: Framework :: Django :: 4.2
Classifier: Intended Audience :: Developers
Classifier: Intended Audience :: End Users/Desktop
Classifier: License :: OSI Approved :: GNU General Public License v3 (GPLv3)
Classifier: Natural Language :: English
Classifier: Natural Language :: French
Classifier: Operating System :: OS Independent
Classifier: Programming Language :: Python :: 3.8
Classifier: Programming Language :: Python :: 3.9
Classifier: Programming Language :: Python :: 3.10
Classifier: Programming Language :: Python :: 3.11
Classifier: Programming Language :: Python :: 3.12
Classifier: Topic :: Database :: Front-Ends
Classifier: Topic :: Office/Business :: Financial :: Accounting
License-File: LICENSE
Requires-Dist: lucterios~=2.7
Requires-Dist: lucterios-contacts~=2.7
Requires-Dist: requests
Requires-Dist: requests-oauthlib~=1.3
Dynamic: author
Dynamic: author-email
Dynamic: classifier
Dynamic: description
Dynamic: home-page
Dynamic: license
Dynamic: license-file
Dynamic: platform
Dynamic: requires-dist
Dynamic: summary
